day3/rf.sv
module rf (
  input logic       clk,
  input logic       reset,
  input logic       wen,
  input logic [1:0] rd,
  input logic [7:0] wdata,
  input logic [1:0] rs1,
  input logic [1:0] rs2,
  output logic [7:0] rdata1,
  output logic [7:0] rdata2,
  output logic [7:0] regs_out [0:3]
);

  logic [7:0] regs [0:3];

  always_ff @(posedge clk or posedge reset) begin
    if (reset) regs <= '{0, 0, 0, 0};
    else if (wen) regs[rd] <= wdata;
  end

  always_comb begin
    rdata1 = regs[rs1];
    rdata2 = regs[rs2];
    regs_out = regs;
  end

endmodule;

day3/alu.sv
module alu (
  input logic [1:0] opcode,
  input logic [7:0] r0,
  input logic [7:0] rdata1,
  input logic [7:0] rdata2,
  input logic [7:0] imm,
  output logic [7:0] rout,
  output logic is_ner0
);

  always_comb begin
    if (opcode == 2'b00) begin
      rout = rdata1 + rdata2;
    end else if (opcode == 2'b10) begin
      rout = imm;
    end else begin 
      rout = 8'b10101010;
    end
    is_ner0 = r0 != rdata2;
  end

endmodule;

day3/dec.sv
module dec (
  input logic [7:0] inst,
  output logic [1:0] rd,
  output logic [1:0] rs1,
  output logic [1:0] rs2,
  output logic [3:0] imm,
  output logic [1:0] opcode,
  output logic       wen,
  output logic [3:0] addr
);

  always_comb begin
    rd[0] = inst[4];
    rd[1] = inst[5];

    rs2[0] = inst[0];
    rs2[1] = inst[1];

    rs1[0] = inst[2];
    rs1[1] = inst[3];

    imm[0] = inst[0];
    imm[1] = inst[1];
    imm[2] = inst[2];
    imm[3] = inst[3];

    addr[0] = inst[2];
    addr[1] = inst[3];
    addr[2] = inst[4];
    addr[3] = inst[5];

    wen = !(inst[6] & inst[7]);

    opcode[0] = inst[6];
    opcode[1] = inst[7];
  end

endmodule;

day3/rom.sv
module rom (
  input logic [3:0] addr,
  output logic [7:0] inst
);

  always_comb begin
    case (addr) inside
            0: inst = 8'b10001010;
            1: inst = 8'b10010000;
            2: inst = 8'b10100000;
            3: inst = 8'b10110001;
            4: inst = 8'b00010111;
            5: inst = 8'b00101001;
            6: inst = 8'b11010001;
            7: inst = 8'b11011111;
      default: inst = 8'b01010101;
    endcase
  end

endmodule

day3/pc.sv
module pc (
  input logic clk,
  input logic reset,
  input logic [3:0] in_addr,
  input logic is_addr,
  output logic [3:0] out_addr
);

  logic [3:0] next_addr;
  always_ff @(posedge clk or posedge reset) begin
    if (reset) begin
      next_addr <= 0;
    end
    else if (is_addr) begin
      next_addr <= in_addr;
    end else begin
      next_addr <= out_addr + 1;
    end
  end
  always_comb begin
    out_addr = next_addr;
  end

endmodule;

day3/main.sv
module main (
  input logic reset,
  input logic clk,
  output logic [3:0] pc,
  output logic [7:0] regs [0:3]
);
  logic is_addr;
  logic [7:0] inst;

  logic [1:0] dec_rd;
  logic [1:0] dec_rs1;
  logic [1:0] dec_rs2;
  logic [3:0] dec_imm;
  logic [7:0] extend_imm;
  logic [1:0] dec_opcode;
  logic       dec_wen;
  logic [3:0] dec_addr;

  logic [7:0] rdata1;
  logic [7:0] rdata2;
  logic [7:0] add_res;
  logic       is_ner0;

  assign extend_imm = {4'b0, dec_imm};

  pc u_pc(
    .clk(clk),
    .reset(reset),
    .in_addr(dec_addr),
    .out_addr(pc),
    .is_addr(is_addr)
  );
  rom u_rom(.addr(pc), .inst(inst));
  dec u_dec(
    .inst(inst),
    .rd(dec_rd),
    .rs1(dec_rs1),
    .rs2(dec_rs2),
    .imm(dec_imm),
    .opcode(dec_opcode),
    .wen(dec_wen),
    .addr(dec_addr)
  );
  alu u_alu(
    .opcode(dec_opcode),
    .r0(regs[0]),
    .rdata1(rdata1),
    .rdata2(rdata2),
    .imm(extend_imm),
    .rout(add_res),
    .is_ner0(is_ner0)
  );
  rf u_rf(
    .clk(clk),
    .reset(reset),
    .wen(dec_wen),
    .rd(dec_rd),
    .wdata(add_res),
    .rs1(dec_rs1),
    .rs2(dec_rs2),
    .rdata1(rdata1),
    .rdata2(rdata2),
    .regs_out(regs)
  );

  always_comb begin
    is_addr = dec_opcode[0] & dec_opcode[1] & is_ner0 & !reset;
  end

endmodule;

day3/waveform.vcd
$version Generated by VerilatedVcd $end
$timescale 1ps $end
 $scope module TOP $end
  $var wire 1 4 reset $end
  $var wire 1 5 clk $end
  $var wire 4 6 pc [3:0] $end
  $var wire 8 7 regs[0] [7:0] $end
  $var wire 8 8 regs[1] [7:0] $end
  $var wire 8 9 regs[2] [7:0] $end
  $var wire 8 : regs[3] [7:0] $end
  $scope module main $end
   $var wire 1 4 reset $end
   $var wire 1 5 clk $end
   $var wire 4 6 pc [3:0] $end
   $var wire 8 7 regs[0] [7:0] $end
   $var wire 8 8 regs[1] [7:0] $end
   $var wire 8 9 regs[2] [7:0] $end
   $var wire 8 : regs[3] [7:0] $end
   $var wire 1 ; is_addr $end
   $var wire 8 # inst [7:0] $end
   $var wire 2 $ dec_rd [1:0] $end
   $var wire 2 % dec_rs1 [1:0] $end
   $var wire 2 & dec_rs2 [1:0] $end
   $var wire 4 ' dec_imm [3:0] $end
   $var wire 8 ( extend_imm [7:0] $end
   $var wire 2 ) dec_opcode [1:0] $end
   $var wire 1 * dec_wen $end
   $var wire 4 + dec_addr [3:0] $end
   $var wire 8 , rdata1 [7:0] $end
   $var wire 8 - rdata2 [7:0] $end
   $var wire 8 . add_res [7:0] $end
   $var wire 1 < is_ner0 $end
   $scope module u_alu $end
    $var wire 2 ) opcode [1:0] $end
    $var wire 8 = r0 [7:0] $end
    $var wire 8 , rdata1 [7:0] $end
    $var wire 8 - rdata2 [7:0] $end
    $var wire 8 ( imm [7:0] $end
    $var wire 8 . rout [7:0] $end
    $var wire 1 < is_ner0 $end
   $upscope $end
   $scope module u_dec $end
    $var wire 8 # inst [7:0] $end
    $var wire 2 $ rd [1:0] $end
    $var wire 2 % rs1 [1:0] $end
    $var wire 2 & rs2 [1:0] $end
    $var wire 4 ' imm [3:0] $end
    $var wire 2 ) opcode [1:0] $end
    $var wire 1 * wen $end
    $var wire 4 + addr [3:0] $end
   $upscope $end
   $scope module u_pc $end
    $var wire 1 5 clk $end
    $var wire 1 4 reset $end
    $var wire 4 + in_addr [3:0] $end
    $var wire 1 ; is_addr $end
    $var wire 4 6 out_addr [3:0] $end
    $var wire 4 / next_addr [3:0] $end
   $upscope $end
   $scope module u_rf $end
    $var wire 1 5 clk $end
    $var wire 1 4 reset $end
    $var wire 1 * wen $end
    $var wire 2 $ rd [1:0] $end
    $var wire 8 . wdata [7:0] $end
    $var wire 2 % rs1 [1:0] $end
    $var wire 2 & rs2 [1:0] $end
    $var wire 8 , rdata1 [7:0] $end
    $var wire 8 - rdata2 [7:0] $end
    $var wire 8 7 regs_out[0] [7:0] $end
    $var wire 8 8 regs_out[1] [7:0] $end
    $var wire 8 9 regs_out[2] [7:0] $end
    $var wire 8 : regs_out[3] [7:0] $end
    $var wire 8 0 regs[0] [7:0] $end
    $var wire 8 1 regs[1] [7:0] $end
    $var wire 8 2 regs[2] [7:0] $end
    $var wire 8 3 regs[3] [7:0] $end
   $upscope $end
   $scope module u_rom $end
    $var wire 4 6 addr [3:0] $end
    $var wire 8 # inst [7:0] $end
   $upscope $end
  $upscope $end
 $upscope $end
$enddefinitions $end


#0
b10010000 #
b01 $
b00 %
b00 &
b0000 '
b00000000 (
b10 )
1*
b0100 +
b00001010 ,
b00001010 -
b00000000 .
b0001 /
b00001010 0
b00000000 1
b00000000 2
b00000000 3
04
15
b0001 6
b00001010 7
b00000000 8
b00000000 9
b00000000 :
0;
0<
b00001010 =
#1
05
#2
b10100000 #
b10 $
b1000 +
b0010 /
15
b0010 6
#3
05
#4
b10110001 #
b11 $
b01 &
b0001 '
b00000001 (
b1100 +
b00000000 -
b00000001 .
b0011 /
15
b0011 6
1<
#5
05
#6
b00010111 #
b01 $
b01 %
b11 &
b0111 '
b00000111 (
b00 )
b0101 +
b00000000 ,
b00000001 -
b0100 /
b00000001 3
15
b0100 6
b00000001 :
#7
05
#8
b00101001 #
b10 $
b10 %
b01 &
b1001 '
b00001001 (
b1010 +
b0101 /
b00000001 1
15
b0101 6
b00000001 8
#9
05
#10
b11010001 #
b01 $
b00 %
b0001 '
b00000001 (
b11 )
0*
b0100 +
b00001010 ,
b10101010 .
b0110 /
b00000001 2
15
b0110 6
b00000001 9
1;
#11
05
#12
b00010111 #
b01 %
b11 &
b0111 '
b00000111 (
b00 )
1*
b0101 +
b00000001 ,
b00000010 .
b0100 /
15
b0100 6
0;
#13
05
#14
b00101001 #
b10 $
b10 %
b01 &
b1001 '
b00001001 (
b1010 +
b00000010 -
b00000011 .
b0101 /
b00000010 1
15
b0101 6
b00000010 8
#15
05
#16
b11010001 #
b01 $
b00 %
b0001 '
b00000001 (
b11 )
0*
b0100 +
b00001010 ,
b10101010 .
b0110 /
b00000011 2
15
b0110 6
b00000011 9
1;
#17
05
#18
b00010111 #
b01 %
b11 &
b0111 '
b00000111 (
b00 )
1*
b0101 +
b00000010 ,
b00000001 -
b00000011 .
b0100 /
15
b0100 6
0;
#19
05
#20
b00101001 #
b10 $
b10 %
b01 &
b1001 '
b00001001 (
b1010 +
b00000011 ,
b00000011 -
b00000110 .
b0101 /
b00000011 1
15
b0101 6
b00000011 8
#21
05
#22
b11010001 #
b01 $
b00 %
b0001 '
b00000001 (
b11 )
0*
b0100 +
b00001010 ,
b10101010 .
b0110 /
b00000110 2
15
b0110 6
b00000110 9
1;
#23
05
#24
b00010111 #
b01 %
b11 &
b0111 '
b00000111 (
b00 )
1*
b0101 +
b00000011 ,
b00000001 -
b00000100 .
b0100 /
15
b0100 6
0;
#25
05
#26
b00101001 #
b10 $
b10 %
b01 &
b1001 '
b00001001 (
b1010 +
b00000110 ,
b00000100 -
b00001010 .
b0101 /
b00000100 1
15
b0101 6
b00000100 8
#27
05
#28
b11010001 #
b01 $
b00 %
b0001 '
b00000001 (
b11 )
0*
b0100 +
b00001010 ,
b10101010 .
b0110 /
b00001010 2
15
b0110 6
b00001010 9
1;
#29
05
#30
b00010111 #
b01 %
b11 &
b0111 '
b00000111 (
b00 )
1*
b0101 +
b00000100 ,
b00000001 -
b00000101 .
b0100 /
15
b0100 6
0;
#31
05
#32
b00101001 #
b10 $
b10 %
b01 &
b1001 '
b00001001 (
b1010 +
b00001010 ,
b00000101 -
b00001111 .
b0101 /
b00000101 1
15
b0101 6
b00000101 8
#33
05
#34
b11010001 #
b01 $
b00 %
b0001 '
b00000001 (
b11 )
0*
b0100 +
b10101010 .
b0110 /
b00001111 2
15
b0110 6
b00001111 9
1;
#35
05
#36
b00010111 #
b01 %
b11 &
b0111 '
b00000111 (
b00 )
1*
b0101 +
b00000101 ,
b00000001 -
b00000110 .
b0100 /
15
b0100 6
0;
#37
05
#38
b00101001 #
b10 $
b10 %
b01 &
b1001 '
b00001001 (
b1010 +
b00001111 ,
b00000110 -
b00010101 .
b0101 /
b00000110 1
15
b0101 6
b00000110 8
#39
05
#40
b11010001 #
b01 $
b00 %
b0001 '
b00000001 (
b11 )
0*
b0100 +
b00001010 ,
b10101010 .
b0110 /
b00010101 2
15
b0110 6
b00010101 9
1;
#41
05
#42
b00010111 #
b01 %
b11 &
b0111 '
b00000111 (
b00 )
1*
b0101 +
b00000110 ,
b00000001 -
b00000111 .
b0100 /
15
b0100 6
0;
#43
05
#44
b00101001 #
b10 $
b10 %
b01 &
b1001 '
b00001001 (
b1010 +
b00010101 ,
b00000111 -
b00011100 .
b0101 /
b00000111 1
15
b0101 6
b00000111 8
#45
05
#46
b11010001 #
b01 $
b00 %
b0001 '
b00000001 (
b11 )
0*
b0100 +
b00001010 ,
b10101010 .
b0110 /
b00011100 2
15
b0110 6
b00011100 9
1;
#47
05
#48
b00010111 #
b01 %
b11 &
b0111 '
b00000111 (
b00 )
1*
b0101 +
b00000111 ,
b00000001 -
b00001000 .
b0100 /
15
b0100 6
0;
#49
05
#50
b00101001 #
b10 $
b10 %
b01 &
b1001 '
b00001001 (
b1010 +
b00011100 ,
b00001000 -
b00100100 .
b0101 /
b00001000 1
15
b0101 6
b00001000 8
#51
05
#52
b11010001 #
b01 $
b00 %
b0001 '
b00000001 (
b11 )
0*
b0100 +
b00001010 ,
b10101010 .
b0110 /
b00100100 2
15
b0110 6
b00100100 9
1;
#53
05
#54
b00010111 #
b01 %
b11 &
b0111 '
b00000111 (
b00 )
1*
b0101 +
b00001000 ,
b00000001 -
b00001001 .
b0100 /
15
b0100 6
0;
#55
05
#56
b00101001 #
b10 $
b10 %
b01 &
b1001 '
b00001001 (
b1010 +
b00100100 ,
b00001001 -
b00101101 .
b0101 /
b00001001 1
15
b0101 6
b00001001 8
#57
05
#58
b11010001 #
b01 $
b00 %
b0001 '
b00000001 (
b11 )
0*
b0100 +
b00001010 ,
b10101010 .
b0110 /
b00101101 2
15
b0110 6
b00101101 9
1;
#59
05
#60
b00010111 #
b01 %
b11 &
b0111 '
b00000111 (
b00 )
1*
b0101 +
b00001001 ,
b00000001 -
b00001010 .
b0100 /
15
b0100 6
0;
#61
05
#62
b00101001 #
b10 $
b10 %
b01 &
b1001 '
b00001001 (
b1010 +
b00101101 ,
b00001010 -
b00110111 .
b0101 /
b00001010 1
15
b0101 6
b00001010 8
0<
#63
05
#64
b11010001 #
b01 $
b00 %
b0001 '
b00000001 (
b11 )
0*
b0100 +
b00001010 ,
b10101010 .
b0110 /
b00110111 2
15
b0110 6
b00110111 9
#65
05
#66
b11011111 #
b11 %
b11 &
b1111 '
b00001111 (
b0111 +
b00000001 ,
b00000001 -
b0111 /
15
b0111 6
1;
1<
